[
  {
    "full_name": "konstantpapp/office_sports_flutter",
    "stargazers_count": 7,
    "open_issues_count": 1,
    "forks_count": 2
  },
  {
    "full_name": "pichsenmeister/drumcommit",
    "stargazers_count": 37,
    "open_issues_count": 0,
    "forks_count": 1
  },
  {
    "full_name": "boyum/green-municipalities",
    "stargazers_count": 3,
    "open_issues_count": 0,
    "forks_count": 1
  },
  {
    "full_name": "cgeo/WhereYouGo",
    "stargazers_count": 70,
    "open_issues_count": 74,
    "forks_count": 30
  },
  {
    "full_name": "fastlane/fastlane",
    "stargazers_count": 36133,
    "open_issues_count": 284,
    "forks_count": 5373
  },
  {
    "full_name": "todogroup/governance",
    "stargazers_count": 80,
    "open_issues_count": 19,
    "forks_count": 105
  },
  {
    "full_name": "gayanvoice/top-github-users",
    "stargazers_count": 1992,
    "open_issues_count": 72,
    "forks_count": 378
  },
  {
    "full_name": "hashicorp/terraform-provider-azurerm",
    "stargazers_count": 3740,
    "open_issues_count": 2251,
    "forks_count": 3814
  },
  {
    "full_name": "Tobiaswk/carwingsflutter",
    "stargazers_count": 12,
    "open_issues_count": 1,
    "forks_count": 5
  },
  {
    "full_name": "factoriotools/factorio-docker",
    "stargazers_count": 682,
    "open_issues_count": 34,
    "forks_count": 177
  },
  {
    "full_name": "covidgreen/covid-green-infra",
    "stargazers_count": 14,
    "open_issues_count": 2,
    "forks_count": 12
  },
  {
    "full_name": "cyph/cyph",
    "stargazers_count": 354,
    "open_issues_count": 15,
    "forks_count": 54
  },
  {
    "full_name": "sonic-pi-net/sonic-pi",
    "stargazers_count": 9678,
    "open_issues_count": 174,
    "forks_count": 879
  },
  {
    "full_name": "andrewning/sortphotos",
    "stargazers_count": 902,
    "open_issues_count": 56,
    "forks_count": 292
  },
  {
    "full_name": "geerlingguy/ansible-vagrant-examples",
    "stargazers_count": 1993,
    "open_issues_count": 2,
    "forks_count": 696
  },
  {
    "full_name": "sindresorhus/awesome",
    "stargazers_count": 230474,
    "open_issues_count": 54,
    "forks_count": 24609
  },
  {
    "full_name": "mozilla/send",
    "stargazers_count": 13189,
    "open_issues_count": 156,
    "forks_count": 1517
  },
  {
    "full_name": "cgeo/cgeo",
    "stargazers_count": 1242,
    "open_issues_count": 711,
    "forks_count": 552
  },
  {
    "full_name": "Nimrodda/WizarDroid",
    "stargazers_count": 170,
    "open_issues_count": 11,
    "forks_count": 81
  },
  {
    "full_name": "PoshCode/PowerShellPracticeAndStyle",
    "stargazers_count": 1839,
    "open_issues_count": 50,
    "forks_count": 267
  },
  {
    "full_name": "PlagueHO/LabBuilder",
    "stargazers_count": 218,
    "open_issues_count": 65,
    "forks_count": 41
  }
]